envguardian/__init__.py
envguardian/_coercers.py
envguardian/_env.py
envguardian/_utils.py
envguardian/_validators.py
envguardian-1.1.0.dist-info/METADATA
envguardian-1.1.0.dist-info/WHEEL
envguardian-1.1.0.dist-info/RECORD
