Metadata-Version: 2.1
Name: envguardian
Version: 1.1.0
Summary: A lightweight environment variables validator in python
Author: Femi Olatubosun
Author-email: femi@zerocomplex.ai
Requires-Python: >=3.6,<4.0
Classifier: Programming Language :: Python :: 3
Classifier: Programming Language :: Python :: 3.6
Classifier: Programming Language :: Python :: 3.7
Classifier: Programming Language :: Python :: 3.8
Classifier: Programming Language :: Python :: 3.9
Classifier: Programming Language :: Python :: 3.10
Classifier: Programming Language :: Python :: 3.11
